{
  "format_version": "1.16.0",
  "minecraft:geometry": [
    {
      "description": {
        "identifier": "geometry.model_7",
        "texture_width": 32,
        "texture_height": 84,
        "visible_bounds_width": 1.625,
        "visible_bounds_height": 2.1875,
        "visible_bounds_offset": [
          0,
          0.59375,
          0
        ]
      },
      "bones": [
        {
          "name": "root",
          "pivot": [
            0,
            0,
            0
          ],
          "cubes": [
            {
              "origin": [
                -4,
                2,
                -3
              ],
              "size": [
                8,
                12,
                6
              ],
              "uv": [
                2,
                2
              ]
            },
            {
              "origin": [
                -3,
                3,
                -3
              ],
              "size": [
                6,
                9,
                1
              ],
              "uv": [
                2,
                22
              ]
            },
            {
              "origin": [
                -3,
                13,
                -3
              ],
              "size": [
                6,
                6,
                6
              ],
              "uv": [
                2,
                34
              ]
            },
            {
              "origin": [
                -1,
                14,
                -4
              ],
              "size": [
                2,
                2,
                2
              ],
              "uv": [
                2,
                48
              ]
            },
            {
              "origin": [
                -5,
                4,
                -2
              ],
              "size": [
                1,
                8,
                4
              ],
              "uv": [
                12,
                48
              ]
            },
            {
              "origin": [
                4,
                4,
                -2
              ],
              "size": [
                1,
                8,
                4
              ],
              "uv": [
                2,
                62
              ]
            },
            {
              "origin": [
                -3,
                0,
                -1
              ],
              "size": [
                3,
                2,
                4
              ],
              "uv": [
                14,
                62
              ]
            },
            {
              "origin": [
                0,
                0,
                -1
              ],
              "size": [
                3,
                2,
                4
              ],
              "uv": [
                2,
                76
              ]
            }
          ]
        }
      ]
    }
  ]
}